[{
    "name": "Startseite",
    "matIcon": "home",
    "id": 0,
    "path": ""
}, {
    "name": "Notentabelle",
    "matIcon": "table_chart",
    "id": 1,
    "path": "notentabelle"
}, {
    "name": "Hausaufgaben",
    "matIcon": "check_box",
    "id": 2,
    "path": "hausaufgaben"
}, {
    "name": "Terminliste",
    "matIcon": "local_mall",
    "id": 3,
    "path": "terminliste"
}, {
    "name": "Prüfungen",
    "matIcon": "schedule",
    "id": 4,
    "path": "pruefungen"
}, {
    "name": "Gemischte Liste",
    "matIcon": "list",
    "id": 5,
    "path": "gemischte_liste"
}, {
    "name": "Einstellung",
    "matIcon": "settings",
    "id": 6,
    "path": "einstellung"
}, {
    "name": "Kalender",
    "matIcon": "calendar_today",
    "id": 7,
    "path": "kalender"
}]
